aidge_export_arm_cortexm
