Metadata-Version: 2.4
Name: aidge_export_arm_cortexm
Version: 0.2.1
Summary: Aidge export for ARM CortexM systems
License: Eclipse Public License 2.0 (EPL-2.0)
Project-URL: Homepage, https://www.deepgreen.ai/en/platform
Project-URL: Documentation, https://eclipse.dev/aidge/
Project-URL: Repository, https://gitlab.eclipse.org/eclipse/aidge/aidge_export_arm_cortexm
Project-URL: Issues, https://gitlab.eclipse.org/eclipse/aidge/aidge_export_arm_cortexm/-/issues/
Project-URL: Changelog, https://gitlab.eclipse.org/eclipse/aidge/aidge_export_arm_cortexm/-/releases
Requires-Python: >=3.10
License-File: LICENSE
Requires-Dist: numpy>=1.21.6
Requires-Dist: onnx>=1.16.0
Requires-Dist: Jinja2>=3.1.2
Requires-Dist: pyocd>=0.35.0
Requires-Dist: pyserial>=3.5
Provides-Extra: dev
Requires-Dist: ipython; extra == "dev"
Requires-Dist: pytest; extra == "dev"
Requires-Dist: pytest-cov; extra == "dev"
Dynamic: license-file
